nltkbleud/__init__.py
nltkbleud/bleud.py
nltkbleud-0.1.0.dist-info/licenses/LICENSE.txt
nltkbleud-0.1.0.dist-info/METADATA
nltkbleud-0.1.0.dist-info/WHEEL
nltkbleud-0.1.0.dist-info/top_level.txt
nltkbleud-0.1.0.dist-info/RECORD
