Metadata-Version: 2.4
Name: nltkbleud
Version: 0.1.0
Summary: package containing the BLEUD class.
Author: pixelpilot24
Author-email: pixelpilot24@gmail.com
License: MIT
Requires-Python: >=3.6
License-File: LICENSE.txt
Dynamic: author
Dynamic: author-email
Dynamic: description
Dynamic: description-content-type
Dynamic: license
Dynamic: license-file
Dynamic: requires-python
Dynamic: summary
